README.txt
setup.py
urllibcache.py
urllibcache.egg-info/PKG-INFO
urllibcache.egg-info/SOURCES.txt
urllibcache.egg-info/dependency_links.txt
urllibcache.egg-info/requires.txt
urllibcache.egg-info/top_level.txt
urllibcache.egg-info/zip-safe