Metadata-Version: 1.0
Name: urllibcache
Version: 1.0.1
Summary: Simple urllib2 caching handler
Home-page: http://svn.plone.org/svn/collective/urllibcache
Author: Florian Schulze
Author-email: florian.schulze@gmx.net
License: GPL
Keywords: urllib cache
Platform: UNKNOWN
Classifier: License :: OSI Approved :: GNU General Public License (GPL)
Classifier: Programming Language :: Python
Classifier: Topic :: Software Development :: Libraries :: Python Modules
